Praktischer Teil/Verilog/CPU/CPU_Verilog/src/imm_decoder.sv
module imm_dec(
    input [31:0] instr,
    output reg [31:0] imm
);

    reg [6:0] opcode;
    reg [4:0] rd;
    reg [2:0] funct3;
    reg [4:0] rs1;
    reg [4:0] rs2;
    reg [6:0] funct7;

    always @(*) begin
        opcode = instr[6:0];
        rd = instr[11:7];
        funct3 = instr[14:12];
        rs1 = instr[19:15];
        rs2 = instr[24:20];
        funct7 = instr[31:25];

        case (opcode)
            7'b0010011:     // I type arithmetic
                imm = {{20{instr[31]}}, instr[31:20]};
            7'b0000011:     // I type load
                imm = {{20{instr[31]}}, instr[31:20]};
            7'b0100011:     // S type
                imm = {{20{instr[31]}}, instr[31:25], instr[11:7]};
            7'b1100011:     // B type
                imm = {{19{instr[31]}}, instr[31], instr[7], instr[30:25], instr[11:8], 1'b0};
            7'b1101111:     // J type jal
                imm = {{11{instr[31]}}, instr[31], instr[19:12], instr[20], instr[30:21], 1'b0};
            7'b1100111:     // I type jalr
                imm = {{20{instr[31]}}, instr[31:20]};
            7'b0110111:     // U type lui
                imm = {instr[31:12], 12'b0};
            7'b0010111:     // U type auipc
                imm = {instr[31:12], 12'b0};
            default:
                imm = 32'b0;
        endcase
    end

endmodule

PraktischerTeil/Verilog/CPU/CPU_Verilog/src/imm_decoder_tb.sv
`timescale 1ns/1ps

module imm_decoder_tb;
    // Declare testbench signals
    reg clk;
    reg rst;
    reg [31:0] instr;
    wire signed [31:0] imm;
    // Instantiate DUT
    imm_dec uut (
        .instr(instr),
        .imm(imm)
    );

    // Clock generation (only if required by DUT)
    initial begin
        clk = 0;
        forever #5 clk = ~clk;
    end

    // Test program
    initial begin
        $dumpfile("tb_imm_decoder.vcd");
        $dumpvars(0, imm_decoder_tb);

        rst = 1;
        instr = 32'b0;
        #2;
        rst = 0;

        instr = 32'h00500093; //addi x1, x0, 5
        #1;
        $display("instr=%h imm=%d", instr, imm);
        instr = 32'hf3800093; //addi x1, x0, -200
        #1;
        $display("instr=%h imm=%d", instr, imm);
        instr = 32'h00112223; //sw x1, 4(x2)
        #1;
        $display("instr=%h imm=%d", instr, imm);
        instr = 32'hf2112c23; //sw x1, -200(x2)
        #1;
        $display("instr=%h imm=%d", instr, imm);
        instr = 32'hf3812083; //lw x1, -200(x2)
        #1;
        $display("instr=%h imm=%d", instr, imm);
        instr = 32'h06412083; //lw x1, 100(x2)
        #1;
        $display("instr=%h imm=%d", instr, imm);
        instr = 32'h12c0006f; //jal x0, 300
        #1;
        $display("instr=%h imm=%d", instr, imm);
        instr = 32'hf39ff06f; //jal x0, -200
        #1;
        $display("instr=%h imm=%d", instr, imm);
        instr = 32'h01e180e7; //jalr x1, x3, 30
        #1;
        $display("instr=%h imm=%d", instr, imm);
        instr = 32'hf34180e7; //jalr x1, x3, -204
        #1;
        $display("instr=%h imm=%d", instr, imm);
        instr = 32'h000c8137; //lui x2, 200
        #1;
        $display("instr=%h imm=%d", instr, imm);

        #100;
        $finish;
    end

    // Timeout watchdog
    initial begin
        #10000;
        $display("ERROR: Test timeout!");
        $finish;
    end

endmodule

PraktischerTeil/Verilog/CPU/CPU_Verilog/src/tb_imm_decoder.vcd
$date
	Sun Dec 14 19:25:28 2025
$end
$version
	Icarus Verilog
$end
$timescale
	1ps
$end
$scope module imm_decoder_tb $end
$var wire 32 ! imm [31:0] $end
$var reg 1 " clk $end
$var reg 32 # instr [31:0] $end
$var reg 1 $ rst $end
$scope module uut $end
$var wire 32 % instr [31:0] $end
$var reg 3 & funct3 [2:0] $end
$var reg 7 ' funct7 [6:0] $end
$var reg 32 ( imm [31:0] $end
$var reg 7 ) opcode [6:0] $end
$var reg 5 * rd [4:0] $end
$var reg 5 + rs1 [4:0] $end
$var reg 5 , rs2 [4:0] $end
$upscope $end
$upscope $end
$enddefinitions $end
$comment Show the parameter values. $end
$dumpall
$end
#0
$dumpvars
b0 ,
b0 +
b0 *
b0 )
b0 (
b0 '
b0 &
b0 %
1$
b0 #
0"
b0 !
$end
#2000
b101 !
b101 (
b101 ,
b1 *
b10011 )
b10100000000000010010011 #
b10100000000000010010011 %
0$
#3000
b11111111111111111111111100111000 !
b11111111111111111111111100111000 (
b1111001 '
b11000 ,
b11110011100000000000000010010011 #
b11110011100000000000000010010011 %
#4000
b100 !
b100 (
b0 '
b1 ,
b10 +
b10 &
b100 *
b100011 )
b100010010001000100011 #
b100010010001000100011 %
#5000
b11111111111111111111111100111000 !
b11111111111111111111111100111000 (
b1111001 '
b11000 *
b11110010000100010010110000100011 #
b11110010000100010010110000100011 %
1"
#6000
b11000 ,
b1 *
b11 )
b11110011100000010010000010000011 #
b11110011100000010010000010000011 %
#7000
b1100100 !
b1100100 (
b11 '
b100 ,
b110010000010010000010000011 #
b110010000010010000010000011 %
#8000
b100101100 !
b100101100 (
b1001 '
b1100 ,
b0 +
b0 &
b0 *
b1101111 )
b10010110000000000000001101111 #
b10010110000000000000001101111 %
#9000
b11111111111111111111111100111000 !
b11111111111111111111111100111000 (
b1111001 '
b11001 ,
b11111 +
b111 &
b11110011100111111111000001101111 #
b11110011100111111111000001101111 %
#10000
b11110 !
b11110 (
b0 '
b11110 ,
b11 +
b0 &
b1 *
b1100111 )
b1111000011000000011100111 #
b1111000011000000011100111 %
0"
#11000
b11111111111111111111111100110100 !
b11111111111111111111111100110100 (
b1111001 '
b10100 ,
b11110011010000011000000011100111 #
b11110011010000011000000011100111 %
#12000
b11001000000000000000 !
b11001000000000000000 (
b0 '
b0 ,
b11001 +
b10 *
b110111 )
b11001000000100110111 #
b11001000000100110111 %
